pycantonese/__init__.py
pycantonese/_punctuation_marks.py
pycantonese/corpus.py
pycantonese/parsing.py
pycantonese/search.py
pycantonese/stop_words.py
pycantonese/util.py
pycantonese/word_segmentation.py
pycantonese/data/hkcancor/FC-001_v2.cha
pycantonese/data/hkcancor/FC-005a_v2.cha
pycantonese/data/hkcancor/FC-005b_v2.cha
pycantonese/data/hkcancor/FC-009b_v.cha
pycantonese/data/hkcancor/FC-011_v.cha
pycantonese/data/hkcancor/FC-012_v.cha
pycantonese/data/hkcancor/FC-013_v.cha
pycantonese/data/hkcancor/FC-018_v.cha
pycantonese/data/hkcancor/FC-019_v.cha
pycantonese/data/hkcancor/FC-020_v.cha
pycantonese/data/hkcancor/FC-022a_v.cha
pycantonese/data/hkcancor/FC-022b_v.cha
pycantonese/data/hkcancor/FC-025_v.cha
pycantonese/data/hkcancor/FC-026_v2.cha
pycantonese/data/hkcancor/FC-027_v2.cha
pycantonese/data/hkcancor/FC-028_v2.cha
pycantonese/data/hkcancor/FC-029_v.cha
pycantonese/data/hkcancor/FC-033_v2.cha
pycantonese/data/hkcancor/FC-035_v2.cha
pycantonese/data/hkcancor/FC-038a_v2.cha
pycantonese/data/hkcancor/FC-038b_v2.cha
pycantonese/data/hkcancor/FC-042_v.cha
pycantonese/data/hkcancor/FC-044_v2.cha
pycantonese/data/hkcancor/FC-045_v2.cha
pycantonese/data/hkcancor/FC-046_v2.cha
pycantonese/data/hkcancor/FC-048_v2.cha
pycantonese/data/hkcancor/FC-049_v2.cha
pycantonese/data/hkcancor/FC-052_v2.cha
pycantonese/data/hkcancor/FC-053_v2.cha
pycantonese/data/hkcancor/FC-055_v2.cha
pycantonese/data/hkcancor/FC-056_v2.cha
pycantonese/data/hkcancor/FC-101_v2.cha
pycantonese/data/hkcancor/FC-103_v2.cha
pycantonese/data/hkcancor/FC-104_v2.cha
pycantonese/data/hkcancor/FC-105_v2.cha
pycantonese/data/hkcancor/FC-106a_v2.cha
pycantonese/data/hkcancor/FC-106b_v2.cha
pycantonese/data/hkcancor/FC-107_v2.cha
pycantonese/data/hkcancor/FC-108a_v2.cha
pycantonese/data/hkcancor/FC-108c_v2.cha
pycantonese/data/hkcancor/FC-108d_v2.cha
pycantonese/data/hkcancor/FC-109a_v2.cha
pycantonese/data/hkcancor/FC-R002a_v2.cha
pycantonese/data/hkcancor/FC-R002b_v2.cha
pycantonese-3.4.0.dist-info/LICENSE.txt
pycantonese-3.4.0.dist-info/METADATA
pycantonese-3.4.0.dist-info/WHEEL
pycantonese-3.4.0.dist-info/top_level.txt
pycantonese-3.4.0.dist-info/RECORD
