Metadata-Version: 2.1
Name: pycantonese
Version: 3.4.0
Summary: Cantonese Linguistics and NLP in Python
Home-page: https://pycantonese.org
Author: Jackson L. Lee
Author-email: jacksonlunlee@gmail.com
License: MIT License
Download-URL: https://pypi.org/project/pycantonese/#files
Project-URL: Source, https://github.com/jacksonllee/pycantonese
Project-URL: Tracker, https://github.com/jacksonllee/pycantonese/issues
Project-URL: Changelog, https://pycantonese.org/changelog.html
Keywords: computational linguistics,natural language processing,NLP,Cantonese,linguistics,corpora,speech,language,Chinese,Jyutping
Platform: UNKNOWN
Classifier: Development Status :: 4 - Beta
Classifier: Environment :: Console
Classifier: Intended Audience :: Developers
Classifier: Intended Audience :: Education
Classifier: Intended Audience :: Information Technology
Classifier: Intended Audience :: Science/Research
Classifier: License :: OSI Approved :: MIT License
Classifier: Natural Language :: Chinese (Traditional)
Classifier: Natural Language :: Cantonese
Classifier: Operating System :: OS Independent
Classifier: Programming Language :: Python :: 3
Classifier: Programming Language :: Python :: 3 :: Only
Classifier: Programming Language :: Python :: 3.7
Classifier: Programming Language :: Python :: 3.8
Classifier: Programming Language :: Python :: 3.9
Classifier: Programming Language :: Python :: 3.10
Classifier: Topic :: Scientific/Engineering
Classifier: Topic :: Scientific/Engineering :: Artificial Intelligence
Classifier: Topic :: Scientific/Engineering :: Human Machine Interfaces
Classifier: Topic :: Scientific/Engineering :: Information Analysis
Classifier: Topic :: Text Processing
Classifier: Topic :: Text Processing :: Filters
Classifier: Topic :: Text Processing :: General
Classifier: Topic :: Text Processing :: Indexing
Classifier: Topic :: Text Processing :: Linguistic
Requires-Python: >=3.7
License-File: LICENSE.txt
